teshu/__init__.py
teshu/enums.py
teshu/generics.py
teshu/manager.py
teshu/mixins.py
teshu/serializers.py
teshu/viewsets.py
teshu/bin/teshu-admin.py
teshu/conf/templates/app/models.py.template
teshu/conf/templates/app/routes.py.template
teshu/conf/templates/app/serializers.py.template
teshu/conf/templates/app/viewsets.py.template
teshu/conf/templates/project/dev.py.template
teshu/conf/templates/project/server.py.template
teshu/conf/templates/project/zappa_settings.json.template
teshu/core/__init__.py
teshu/core/management/__init__.py
teshu/core/management/base.py
teshu/core/management/commands/__init__.py
teshu/core/management/commands/help.py
teshu/core/management/commands/migrate.py
teshu/core/management/commands/shell.py
teshu/core/management/commands/startapp.py
teshu/core/management/commands/startproject.py
teshu/db/__init__.py
teshu/db/models.py
teshu-0.0.2.data/scripts/teshu-admin.py
teshu-0.0.2.dist-info/METADATA
teshu-0.0.2.dist-info/RECORD
teshu-0.0.2.dist-info/WHEEL
teshu-0.0.2.dist-info/entry_points.txt
teshu-0.0.2.dist-info/top_level.txt
